README.md
setup.py
picturizer/__init__.py
picturizer/picturizer.py
picturizer.egg-info/PKG-INFO
picturizer.egg-info/SOURCES.txt
picturizer.egg-info/dependency_links.txt
picturizer.egg-info/entry_points.txt
picturizer.egg-info/requires.txt
picturizer.egg-info/top_level.txt