Metadata-Version: 1.2
Name: picturizer
Version: 1.0.1
Summary: Transform picture into picture-like string
Home-page: https://github.com/Monsoir/picturizer
Author: Monsoir
Author-email: monwingyeung@gmail.com
License: MIT License
Keywords: image,string,image to string,Monsoir
Platform: any
Classifier: Programming Language :: Python :: 3.6
Requires-Python: >3
